spotify_jam/__init__.py
spotify_jam/main.py
spotify_jam-0.2.dist-info/METADATA
spotify_jam-0.2.dist-info/WHEEL
spotify_jam-0.2.dist-info/top_level.txt
spotify_jam-0.2.dist-info/RECORD
