Metadata-Version: 2.1
Name: spotify-jam
Version: 0.2
Summary: spotify-jam is a package that allows you to manage Spotify Jams
